MANIFEST.in
setup.py
push_to_talk.egg-info/PKG-INFO
push_to_talk.egg-info/SOURCES.txt
push_to_talk.egg-info/dependency_links.txt
push_to_talk.egg-info/entry_points.txt
push_to_talk.egg-info/requires.txt
push_to_talk.egg-info/top_level.txt
push_to_talk_app/__init__.py
push_to_talk_app/application.py
push_to_talk_app/key_monitor.py
push_to_talk_app/icons/mute.png
push_to_talk_app/icons/setkey.png
push_to_talk_app/icons/talk.png
push_to_talk_app/interfaces/__init__.py
push_to_talk_app/interfaces/pulse_audio.py
push_to_talk_app/interfaces/skype.py