Metadata-Version: 1.0
Name: push-to-talk
Version: 1.0.2
Summary: Push-to-talk functionality for Linux
Home-page: http://bitbucket.org/latestrevision/linux-push-to-talk/
Author: Adam Coddington
Author-email: me@adamcoddington.net
License: UNKNOWN
Platform: UNKNOWN
Classifier: License :: OSI Approved :: MIT License
Classifier: Operating System :: OS Independent
Classifier: Programming Language :: Python
Classifier: Topic :: Utilities
